grako/__init__.py
grako/__main__.py
grako/_config.py
grako/_unicode_characters.py
grako/_version.py
grako/ast.py
grako/bootstrap.py
grako/buffering.py
grako/color.py
grako/containers.py
grako/contexts.py
grako/diagrams.py
grako/exceptions.py
grako/grammars.py
grako/infos.py
grako/model.py
grako/objectmodel.py
grako/parser.py
grako/parsing.py
grako/rendering.py
grako/semantics.py
grako/symtables.py
grako/synth.py
grako/tool.py
grako/util.py
grako/walkers.py
grako/yaml.py
grako/codegen/__init__.py
grako/codegen/cgbase.py
grako/codegen/objectmodel.py
grako/codegen/python.py
grako/test/__init__.py
grako/test/__main__.py
grako/test/ast_test.py
grako/test/buffering_test.py
grako/test/codegen_test.py
grako/test/diagram_test.py
grako/test/model_test.py
grako/test/parsing_test.py
grako/test/pickle_test.py
grako/test/grammar/__init__.py
grako/test/grammar/directive_test.py
grako/test/grammar/join_test.py
grako/test/grammar/keyword_test.py
grako/test/grammar/left_recursion_test.py
grako/test/grammar/parameter_test.py
grako/test/grammar/pattern_test.py
grako/test/grammar/pretty_test.py
grako/test/grammar/semantics_test.py
grako/test/grammar/stateful_test.py
grako/test/grammar/syntax_test.py
grako/test/zzz_bootstrap/__init__.py
grako/test/zzz_bootstrap/bootstrap_test.py
grako-3.22.0.dist-info/DESCRIPTION.rst
grako-3.22.0.dist-info/LICENSE.txt
grako-3.22.0.dist-info/METADATA
grako-3.22.0.dist-info/RECORD
grako-3.22.0.dist-info/WHEEL
grako-3.22.0.dist-info/entry_points.txt
grako-3.22.0.dist-info/metadata.json
grako-3.22.0.dist-info/top_level.txt
