Metadata-Version: 2.0
Name: grako
Version: 3.22.0
Summary: Grako takes a grammar in a variation of EBNF as input, and outputs a memoizing PEG/Packrat parser in Python.
Home-page: https://bitbucket.org/neogeny/grako
Author: Juancarlo Añez
Author-email: apalala@gmail.com
License: BSD License
Platform: UNKNOWN
Classifier: Development Status :: 5 - Production/Stable
Classifier: License :: OSI Approved :: BSD License
Classifier: Natural Language :: English
Classifier: Intended Audience :: Developers
Classifier: Intended Audience :: Science/Research
Classifier: Environment :: Console
Classifier: Operating System :: OS Independent
Classifier: Programming Language :: Python :: 2.7
Classifier: Programming Language :: Python :: 3.4
Classifier: Programming Language :: Python :: 3.5
Classifier: Programming Language :: Python :: 3.6
Classifier: Programming Language :: Python :: Implementation :: PyPy
Classifier: Programming Language :: Cython
Classifier: Topic :: Software Development :: Code Generators
Classifier: Topic :: Software Development :: Compilers
Classifier: Topic :: Software Development :: Interpreters
Classifier: Topic :: Text Processing :: General
Provides-Extra: future-regex
Requires-Dist: regex; extra == 'future-regex'
